{
    "activeTabId": "2fa",
    "tabs": [
        {
            "id": "profile",
            "title": "Account",
            "path": "./profile-settings/account-setting.ejs",
            "data": {
                "avatarSrc": "/imgs/avatar.svg",
                "username": "TanukiCode",
                "email": "tanukicode@gmail.com",
                "accountStatus": "Default",
                "twoFAStatus": "Disabled",
                "idVerification": "Not verified"
            }
        },
        {
            "id": "referrals",
            "title": "Referrals",
            "path": "./profile-settings/referrals-setting.ejs",
            "data": {
                "referralLink": "https://null/signup?ref=1",
                "totalRewards": "0",
                "totalRewardsCurrency": "USDT",
                "inviterRewards": "0.00",
                "inviterRewardsCurrency": "USDT",
                "rewardNote": "You’re earning 15% of the trading fees your referrals pay.",
                "totalInvited": 0
            }
        },
        {
            "id": "password",
            "title": "Password",
            "path": "./profile-settings/password-setting.ejs",
            "data": {
                "formTitle": "Change password",
                "newPasswordLabel": "New password",
                "confirmPasswordLabel": "Confirm new password",
                "submitButtonText": "Save"
            }
        },
        {
            "id": "2fa",
            "title": "2FA",
            "path": "./profile-settings/2fa-setting.ejs",
            "data": {
                "qrCodeUrl": "https://api.qrserver.com/v1/create-qr-code/?data=otpauth://totp/tanukicode@gmail.com%20(null)?secret=NSEKXMFL4MGU3U37JF7LIIOVZ4X4CEN7&size=215x215&ecc=M",
                "manualCode": "NSEKXMFL4MGU3U37JF7LIIOVZ4X4CEN7",
                "storeLinks": [
                    {
                        "href": "https://play.google.com/store/apps/details?id=com.google.android.apps.authenticator2",
                        "img": "/imgs/android.svg"
                    },
                    {
                        "href": "https://apps.apple.com/app/google-authenticator/id388497605",
                        "img": "/imgs/apple-black.svg"
                    },
                    {
                        "href": "https://chrome.google.com/webstore/detail/authenticator/bhghoamapcdpbohphigoooaddinpkbai",
                        "img": "/imgs/google-chrome.svg"
                    },
                    {
                        "href": "https://chrome.google.com/webstore/detail/authenticator/bhghoamapcdpbohphigoooaddinpkbai",
                        "img": "/imgs/lion.svg"
                    }
                ]
            }
        }
    ]
}
