{
    "activeTabId": "id-setting",
    "tabs": [
        {
            "id": "profile",
            "title": "Account",
            "path": "./profile-settings/account-setting.ejs",
            "data": {
                "avatarSrc": "/imgs/avatar.svg",
                "username": "TanukiCode",
                "email": "tanukicode@gmail.com",
                "accountStatus": "Default",
                "twoFAStatus": "Disabled",
                "idVerification": "Not verified"
            }
        },
        {
            "id": "referrals",
            "title": "Referrals",
            "path": "./profile-settings/referrals-setting.ejs",
            "data": {
                "referralLink": "https://null/signup?ref=1",
                "totalRewards": "0",
                "totalRewardsCurrency": "USDT",
                "inviterRewards": "0.00",
                "inviterRewardsCurrency": "USDT",
                "rewardNote": "You’re earning 15% of the trading fees your referrals pay.",
                "totalInvited": 0
            }
        },
        {
            "id": "password",
            "title": "Password",
            "path": "./profile-settings/password-setting.ejs",
            "data": {
                "formTitle": "Change password",
                "newPasswordLabel": "New password",
                "confirmPasswordLabel": "Confirm new password",
                "submitButtonText": "Save"
            }
        },
        {
            "id": "2fa",
            "title": "2FA",
            "path": "./profile-settings/2fa-setting.ejs",
            "data": {
                "qrCodeUrl": "https://api.qrserver.com/v1/create-qr-code/?data=otpauth://totp/tanukicode@gmail.com%20(null)?secret=NSEKXMFL4MGU3U37JF7LIIOVZ4X4CEN7&size=215x215&ecc=M",
                "manualCode": "NSEKXMFL4MGU3U37JF7LIIOVZ4X4CEN7",
                "storeLinks": [
                    {
                        "href": "https://play.google.com/store/apps/details?id=com.google.android.apps.authenticator2",
                        "img": "/imgs/android.svg"
                    },
                    {
                        "href": "https://apps.apple.com/app/google-authenticator/id388497605",
                        "img": "/imgs/apple-black.svg"
                    },
                    {
                        "href": "https://chrome.google.com/webstore/detail/authenticator/bhghoamapcdpbohphigoooaddinpkbai",
                        "img": "/imgs/google-chrome.svg"
                    },
                    {
                        "href": "https://chrome.google.com/webstore/detail/authenticator/bhghoamapcdpbohphigoooaddinpkbai",
                        "img": "/imgs/lion.svg"
                    }
                ]
            }
        },
        {
            "id": "id-setting",
            "title": "ID Verification",
            "path": "./profile-settings/id-setting.ejs",
            "data": {
                "countries": [
                    { "code": "af", "name": "Afghanistan" },
                    { "code": "ax", "name": "Åland Islands" },
                    { "code": "al", "name": "Albania" },
                    { "code": "nl", "name": "Netherlands" },
                    { "code": "dz", "name": "Algeria" },
                    { "code": "as", "name": "American Samoa" },
                    { "code": "ad", "name": "Andorra" },
                    { "code": "ao", "name": "Angola" },
                    { "code": "ai", "name": "Anguilla" },
                    { "code": "aq", "name": "Antarctica" },
                    { "code": "ag", "name": "Antigua and Barbuda" },
                    { "code": "ar", "name": "Argentina" },
                    { "code": "am", "name": "Armenia" },
                    { "code": "aw", "name": "Aruba" },
                    { "code": "au", "name": "Australia" },
                    { "code": "at", "name": "Austria" },
                    { "code": "az", "name": "Azerbaijan" },
                    { "code": "bs", "name": "Bahamas" },
                    { "code": "bh", "name": "Bahrain" },
                    { "code": "bd", "name": "Bangladesh" }
                ],
                "selectedCountry": "nl",
                "documentTypes": [
                    { "value": "Passport", "label": "Passport" },
                    { "value": "Government - Issued ID card", "label": "Government - Issued ID card" },
                    { "value": "Driver’s license", "label": "Driver’s license" }
                ],
                "selectedDocumentType": "Passport"
            }
        }
    ]
}
